{"nodes": [{"id": "report_securityAudit", "label": "Security Audit Report", "file_type": "document", "source_file": "report.md", "source_location": "Executive Summary", "source_url": null, "captured_at": null, "author": null, "contributor": null}, {"id": "report_bug001StaleClosure", "label": "BUG-001: Stale Closure Drops Quiz Scores", "file_type": "document", "source_file": "report.md", "source_location": "BUG-001", "source_url": null, "captured_at": null, "author": null, "contributor": null}, {"id": "report_bug002DebugLogs", "label": "BUG-002: Debug Logs Leak PII", "file_type": "document", "source_file": "report.md", "source_location": "BUG-002", "source_url": null, "captured_at": null, "author": null, "contributor": null}, {"id": "report_bug003BiasedShuffle", "label": "BUG-003: Biased MCQ Shuffle", "file_type": "document", "source_file": "report.md", "source_location": "BUG-003", "source_url": null, "captured_at": null, "author": null, "contributor": null}, {"id": "report_bug004PromptInjection", "label": "BUG-004: Prompt Injection via System Instruction", "file_type": "document", "source_file": "report.md", "source_location": "BUG-004", "source_url": null, "captured_at": null, "author": null, "contributor": null}, {"id": "report_bug005UnauthAPI", "label": "BUG-005: Unauthenticated API Endpoint", "file_type": "document", "source_file": "report.md", "source_location": "BUG-005", "source_url": null, "captured_at": null, "author": null, "contributor": null}, {"id": "report_bug006RateLimitBypass", "label": "BUG-006: Rate Limiting Bypassable via IP Rotation", "file_type": "document", "source_file": "report.md", "source_location": "BUG-006", "source_url": null, "captured_at": null, "author": null, "contributor": null}, {"id": "report_bug007AdminAccess", "label": "BUG-007: Admin Panel Accessible to All Users", "file_type": "document", "source_file": "report.md", "source_location": "BUG-007", "source_url": null, "captured_at": null, "author": null, "contributor": null}, {"id": "report_bug008UserEnumeration", "label": "BUG-008: User Enumeration via Auth Errors", "file_type": "document", "source_file": "report.md", "source_location": "BUG-008", "source_url": null, "captured_at": null, "author": null, "contributor": null}, {"id": "report_bug009EmailExposure", "label": "BUG-009: Peer Email Exposure via select('*')", "file_type": "document", "source_file": "report.md", "source_location": "BUG-009", "source_url": null, "captured_at": null, "author": null, "contributor": null}, {"id": "report_bug010APIKeyExposure", "label": "BUG-010: Live API Key in .env File", "file_type": "document", "source_file": "report.md", "source_location": "BUG-010", "source_url": null, "captured_at": null, "author": null, "contributor": null}, {"id": "report_bug011FetchTimeout", "label": "BUG-011: No Fetch Timeout (UI Hangs)", "file_type": "document", "source_file": "report.md", "source_location": "BUG-011", "source_url": null, "captured_at": null, "author": null, "contributor": null}, {"id": "report_bug012LocalhostOrigin", "label": "BUG-012: allowLocalhostAsSecureOrigin in Production", "file_type": "document", "source_file": "report.md", "source_location": "BUG-012", "source_url": null, "captured_at": null, "author": null, "contributor": null}, {"id": "report_bug013LeaderboardSpinner", "label": "BUG-013: Leaderboard Infinite Spinner on Error", "file_type": "document", "source_file": "report.md", "source_location": "BUG-013", "source_url": null, "captured_at": null, "author": null, "contributor": null}, {"id": "report_bug014ParseIntRadix", "label": "BUG-014: parseInt Without Radix", "file_type": "document", "source_file": "report.md", "source_location": "BUG-014", "source_url": null, "captured_at": null, "author": null, "contributor": null}, {"id": "report_open01CDNNoSRI", "label": "OPEN-01: CDN Importmap Without SRI Hashes", "file_type": "document", "source_file": "report.md", "source_location": "OPEN-01", "source_url": null, "captured_at": null, "author": null, "contributor": null}, {"id": "report_open02MissingSecHeaders", "label": "OPEN-02: Missing Security Headers on SPA Routes", "file_type": "document", "source_file": "report.md", "source_location": "OPEN-02", "source_url": null, "captured_at": null, "author": null, "contributor": null}, {"id": "report_fisherYatesShuffle", "label": "Fisher-Yates Unbiased Shuffle Fix", "file_type": "document", "source_file": "report.md", "source_location": "BUG-003", "source_url": null, "captured_at": null, "author": null, "contributor": null}, {"id": "report_abortControllerTimeout", "label": "AbortController 30s Fetch Timeout Fix", "file_type": "document", "source_file": "report.md", "source_location": "BUG-011", "source_url": null, "captured_at": null, "author": null, "contributor": null}, {"id": "report_promptInjectionFix", "label": "Prompt Injection Prevention: User Data in History Turn", "file_type": "document", "source_file": "report.md", "source_location": "BUG-004", "source_url": null, "captured_at": null, "author": null, "contributor": null}], "edges": [{"source": "report_securityAudit", "target": "productspec_cogniStruct", "relation": "references", "confidence": "EXTRACTED", "confidence_score": 1.0, "source_file": "report.md", "source_location": "Executive Summary", "weight": 1.0}, {"source": "report_bug001StaleClosure", "target": "productspec_quiz", "relation": "references", "confidence": "EXTRACTED", "confidence_score": 1.0, "source_file": "report.md", "source_location": "BUG-001", "weight": 1.0}, {"source": "report_bug002DebugLogs", "target": "productspec_quiz", "relation": "references", "confidence": "EXTRACTED", "confidence_score": 1.0, "source_file": "report.md", "source_location": "BUG-002", "weight": 1.0}, {"source": "report_bug002DebugLogs", "target": "productspec_leaderboard", "relation": "references", "confidence": "EXTRACTED", "confidence_score": 1.0, "source_file": "report.md", "source_location": "BUG-002", "weight": 1.0}, {"source": "report_bug003BiasedShuffle", "target": "productspec_quiz", "relation": "references", "confidence": "EXTRACTED", "confidence_score": 1.0, "source_file": "report.md", "source_location": "BUG-003", "weight": 1.0}, {"source": "report_fisherYatesShuffle", "target": "report_bug003BiasedShuffle", "relation": "rationale_for", "confidence": "EXTRACTED", "confidence_score": 1.0, "source_file": "report.md", "source_location": "BUG-003", "weight": 1.0}, {"source": "report_bug004PromptInjection", "target": "productspec_doubtSolver", "relation": "references", "confidence": "EXTRACTED", "confidence_score": 1.0, "source_file": "report.md", "source_location": "BUG-004", "weight": 1.0}, {"source": "report_promptInjectionFix", "target": "report_bug004PromptInjection", "relation": "rationale_for", "confidence": "EXTRACTED", "confidence_score": 1.0, "source_file": "report.md", "source_location": "BUG-004", "weight": 1.0}, {"source": "report_bug005UnauthAPI", "target": "productspec_vercelServerless", "relation": "references", "confidence": "EXTRACTED", "confidence_score": 1.0, "source_file": "report.md", "source_location": "BUG-005", "weight": 1.0}, {"source": "report_bug006RateLimitBypass", "target": "productspec_rateLimiting", "relation": "references", "confidence": "EXTRACTED", "confidence_score": 1.0, "source_file": "report.md", "source_location": "BUG-006", "weight": 1.0}, {"source": "report_bug007AdminAccess", "target": "productspec_adminDashboard", "relation": "references", "confidence": "EXTRACTED", "confidence_score": 1.0, "source_file": "report.md", "source_location": "BUG-007", "weight": 1.0}, {"source": "report_bug008UserEnumeration", "target": "productspec_jwtAuth", "relation": "references", "confidence": "EXTRACTED", "confidence_score": 1.0, "source_file": "report.md", "source_location": "BUG-008", "weight": 1.0}, {"source": "report_bug009EmailExposure", "target": "productspec_community", "relation": "references", "confidence": "EXTRACTED", "confidence_score": 1.0, "source_file": "report.md", "source_location": "BUG-009", "weight": 1.0}, {"source": "report_bug009EmailExposure", "target": "productspec_profilesTable", "relation": "references", "confidence": "EXTRACTED", "confidence_score": 1.0, "source_file": "report.md", "source_location": "BUG-009", "weight": 1.0}, {"source": "report_bug010APIKeyExposure", "target": "productspec_geminiAI", "relation": "references", "confidence": "EXTRACTED", "confidence_score": 1.0, "source_file": "report.md", "source_location": "BUG-010", "weight": 1.0}, {"source": "report_bug011FetchTimeout", "target": "productspec_vercelServerless", "relation": "references", "confidence": "EXTRACTED", "confidence_score": 1.0, "source_file": "report.md", "source_location": "BUG-011", "weight": 1.0}, {"source": "report_abortControllerTimeout", "target": "report_bug011FetchTimeout", "relation": "rationale_for", "confidence": "EXTRACTED", "confidence_score": 1.0, "source_file": "report.md", "source_location": "BUG-011", "weight": 1.0}, {"source": "report_bug012LocalhostOrigin", "target": "productspec_oneSignal", "relation": "references", "confidence": "EXTRACTED", "confidence_score": 1.0, "source_file": "report.md", "source_location": "BUG-012", "weight": 1.0}, {"source": "report_bug013LeaderboardSpinner", "target": "productspec_leaderboard", "relation": "references", "confidence": "EXTRACTED", "confidence_score": 1.0, "source_file": "report.md", "source_location": "BUG-013", "weight": 1.0}, {"source": "report_bug014ParseIntRadix", "target": "productspec_vercelServerless", "relation": "references", "confidence": "EXTRACTED", "confidence_score": 1.0, "source_file": "report.md", "source_location": "BUG-014", "weight": 1.0}, {"source": "report_open01CDNNoSRI", "target": "indexhtml_importmap", "relation": "references", "confidence": "EXTRACTED", "confidence_score": 1.0, "source_file": "report.md", "source_location": "OPEN-01", "weight": 1.0}, {"source": "report_open02MissingSecHeaders", "target": "productspec_corsPolicy", "relation": "references", "confidence": "EXTRACTED", "confidence_score": 1.0, "source_file": "report.md", "source_location": "OPEN-02", "weight": 1.0}, {"source": "report_securityAudit", "target": "report_bug001StaleClosure", "relation": "references", "confidence": "EXTRACTED", "confidence_score": 1.0, "source_file": "report.md", "source_location": "Issue Index", "weight": 1.0}, {"source": "report_securityAudit", "target": "report_bug002DebugLogs", "relation": "references", "confidence": "EXTRACTED", "confidence_score": 1.0, "source_file": "report.md", "source_location": "Issue Index", "weight": 1.0}, {"source": "report_securityAudit", "target": "report_bug003BiasedShuffle", "relation": "references", "confidence": "EXTRACTED", "confidence_score": 1.0, "source_file": "report.md", "source_location": "Issue Index", "weight": 1.0}, {"source": "report_securityAudit", "target": "report_bug004PromptInjection", "relation": "references", "confidence": "EXTRACTED", "confidence_score": 1.0, "source_file": "report.md", "source_location": "Issue Index", "weight": 1.0}, {"source": "report_securityAudit", "target": "report_bug005UnauthAPI", "relation": "references", "confidence": "EXTRACTED", "confidence_score": 1.0, "source_file": "report.md", "source_location": "Issue Index", "weight": 1.0}, {"source": "report_securityAudit", "target": "report_bug006RateLimitBypass", "relation": "references", "confidence": "EXTRACTED", "confidence_score": 1.0, "source_file": "report.md", "source_location": "Issue Index", "weight": 1.0}, {"source": "report_securityAudit", "target": "report_bug007AdminAccess", "relation": "references", "confidence": "EXTRACTED", "confidence_score": 1.0, "source_file": "report.md", "source_location": "Issue Index", "weight": 1.0}, {"source": "report_securityAudit", "target": "report_bug008UserEnumeration", "relation": "references", "confidence": "EXTRACTED", "confidence_score": 1.0, "source_file": "report.md", "source_location": "Issue Index", "weight": 1.0}, {"source": "report_securityAudit", "target": "report_bug009EmailExposure", "relation": "references", "confidence": "EXTRACTED", "confidence_score": 1.0, "source_file": "report.md", "source_location": "Issue Index", "weight": 1.0}, {"source": "report_securityAudit", "target": "report_bug010APIKeyExposure", "relation": "references", "confidence": "EXTRACTED", "confidence_score": 1.0, "source_file": "report.md", "source_location": "Issue Index", "weight": 1.0}, {"source": "report_securityAudit", "target": "report_bug011FetchTimeout", "relation": "references", "confidence": "EXTRACTED", "confidence_score": 1.0, "source_file": "report.md", "source_location": "Issue Index", "weight": 1.0}, {"source": "report_securityAudit", "target": "report_bug012LocalhostOrigin", "relation": "references", "confidence": "EXTRACTED", "confidence_score": 1.0, "source_file": "report.md", "source_location": "Issue Index", "weight": 1.0}, {"source": "report_securityAudit", "target": "report_bug013LeaderboardSpinner", "relation": "references", "confidence": "EXTRACTED", "confidence_score": 1.0, "source_file": "report.md", "source_location": "Issue Index", "weight": 1.0}, {"source": "report_securityAudit", "target": "report_bug014ParseIntRadix", "relation": "references", "confidence": "EXTRACTED", "confidence_score": 1.0, "source_file": "report.md", "source_location": "Issue Index", "weight": 1.0}, {"source": "report_securityAudit", "target": "report_open01CDNNoSRI", "relation": "references", "confidence": "EXTRACTED", "confidence_score": 1.0, "source_file": "report.md", "source_location": "Issue Index", "weight": 1.0}, {"source": "report_securityAudit", "target": "report_open02MissingSecHeaders", "relation": "references", "confidence": "EXTRACTED", "confidence_score": 1.0, "source_file": "report.md", "source_location": "Issue Index", "weight": 1.0}, {"source": "report_bug007AdminAccess", "target": "productspec_rlsSecurity", "relation": "conceptually_related_to", "confidence": "INFERRED", "confidence_score": 0.75, "source_file": "report.md", "source_location": "BUG-007", "weight": 0.75}], "hyperedges": [{"id": "security_audit_coverage", "label": "Security Audit Bug Coverage", "nodes": ["report_securityAudit", "report_bug004PromptInjection", "report_bug005UnauthAPI", "report_bug006RateLimitBypass"], "relation": "participate_in", "confidence": "EXTRACTED", "confidence_score": 0.95, "source_file": "report.md"}]}